configs/standard_trace_schema.json
tracegen/__init__.py
tracegen/api.py
tracegen/data_fetcher.py
tracegen/utils.py
tracegen/adapters/__init__.py
tracegen/adapters/cpu_long_adapter.py
tracegen/adapters/cpu_short_adapter.py
tracegen/adapters/gfx_adapter.py
tracegen/perfetto/__init__.py
tracegen/perfetto/perfetto_trace_manager.py
tracegen/perfetto/perfetto_trace_pb2.py
tracegen-1.0.0.dist-info/METADATA
tracegen-1.0.0.dist-info/WHEEL
tracegen-1.0.0.dist-info/entry_points.txt
tracegen-1.0.0.dist-info/top_level.txt
tracegen-1.0.0.dist-info/RECORD
