Metadata-Version: 2.4
Name: tracegen
Version: 1.0.0
Summary: 标准格式 Trace 生成工具，将原始数据一键转为 Perfetto trace 文件
Home-page: https://github.com/merlotliu/tracegen
Author: liumoulu
Author-email: liumoulu@lixiang.com
Classifier: Development Status :: 4 - Beta
Classifier: Intended Audience :: Developers
Classifier: License :: OSI Approved :: MIT License
Classifier: Operating System :: OS Independent
Classifier: Programming Language :: Python :: 3
Classifier: Programming Language :: Python :: 3.8
Classifier: Programming Language :: Python :: 3.9
Classifier: Programming Language :: Python :: 3.10
Classifier: Programming Language :: Python :: 3.11
Classifier: Topic :: Software Development
Classifier: Topic :: System :: Systems Administration
Classifier: Topic :: Utilities
Requires-Python: >=3.8
Requires-Dist: protobuf>=4.25.1
Requires-Dist: requests
Requires-Dist: click
Dynamic: author
Dynamic: author-email
Dynamic: classifier
Dynamic: description
Dynamic: description-content-type
Dynamic: home-page
Dynamic: requires-dist
Dynamic: requires-python
Dynamic: summary
